[{"id":"115807","name":"ÅHUS","state_code":"M","country_code":"SE"},{"id":"115808","name":"ÅKARP","state_code":"M","country_code":"SE"},{"id":"115809","name":"ANDERSLÖV","state_code":"M","country_code":"SE"},{"id":"115810","name":"ÄNGELHOLM","state_code":"M","country_code":"SE"},{"id":"115811","name":"ARLÖV","state_code":"M","country_code":"SE"},{"id":"115812","name":"ASMUNDTORP","state_code":"M","country_code":"SE"},{"id":"115813","name":"ÅSTORP","state_code":"M","country_code":"SE"},{"id":"115814","name":"BARA","state_code":"M","country_code":"SE"},{"id":"115815","name":"BÅRSLÖV","state_code":"M","country_code":"SE"},{"id":"115816","name":"BÅSTAD","state_code":"M","country_code":"SE"},{"id":"115817","name":"BILLEBERGA","state_code":"M","country_code":"SE"},{"id":"115818","name":"BILLESHOLM","state_code":"M","country_code":"SE"},{"id":"115819","name":"BJÄRNUM","state_code":"M","country_code":"SE"},{"id":"115820","name":"BJÄRRED","state_code":"M","country_code":"SE"},{"id":"115821","name":"BJUV","state_code":"M","country_code":"SE"},{"id":"115822","name":"BLENTARP","state_code":"M","country_code":"SE"},{"id":"115823","name":"BROBY","state_code":"M","country_code":"SE"},{"id":"115824","name":"BROMÖLLA","state_code":"M","country_code":"SE"},{"id":"115825","name":"BUNKEFLOSTRAND","state_code":"M","country_code":"SE"},{"id":"115826","name":"DALBY","state_code":"M","country_code":"SE"},{"id":"115827","name":"DEGEBERGA","state_code":"M","country_code":"SE"},{"id":"115828","name":"EKEBY","state_code":"M","country_code":"SE"},{"id":"115829","name":"ESLÖV","state_code":"M","country_code":"SE"},{"id":"115830","name":"FÄRLÖV","state_code":"M","country_code":"SE"},{"id":"115831","name":"FJÄLKINGE","state_code":"M","country_code":"SE"},{"id":"115832","name":"FÖRSLÖV","state_code":"M","country_code":"SE"},{"id":"115833","name":"FURULUND","state_code":"M","country_code":"SE"},{"id":"115834","name":"GANTOFTA","state_code":"M","country_code":"SE"},{"id":"115835","name":"GÄRSNÄS","state_code":"M","country_code":"SE"},{"id":"115836","name":"GENARP","state_code":"M","country_code":"SE"},{"id":"115837","name":"GLIMÅKRA","state_code":"M","country_code":"SE"},{"id":"115838","name":"GLUMSLÖV","state_code":"M","country_code":"SE"},{"id":"115839","name":"HÄLJARP","state_code":"M","country_code":"SE"},{"id":"115840","name":"HAMMAR","state_code":"M","country_code":"SE"},{"id":"115841","name":"HANASKOG","state_code":"M","country_code":"SE"},{"id":"115842","name":"HÄSSLEHOLM","state_code":"M","country_code":"SE"},{"id":"115843","name":"HÄSTVEDA","state_code":"M","country_code":"SE"},{"id":"115844","name":"HELSINGBORG","state_code":"M","country_code":"SE"},{"id":"115845","name":"HITTARP","state_code":"M","country_code":"SE"},{"id":"115846","name":"HJÄRNARP","state_code":"M","country_code":"SE"},{"id":"115847","name":"HJÄRUP","state_code":"M","country_code":"SE"},{"id":"115848","name":"HOFTERUP","state_code":"M","country_code":"SE"},{"id":"115849","name":"HÖGANÄS","state_code":"M","country_code":"SE"},{"id":"115850","name":"HÖKÖPINGE","state_code":"M","country_code":"SE"},{"id":"115851","name":"HÖLLVIKEN","state_code":"M","country_code":"SE"},{"id":"115852","name":"HÖÖR","state_code":"M","country_code":"SE"},{"id":"115853","name":"HÖRBY","state_code":"M","country_code":"SE"},{"id":"115854","name":"HYLLINGE","state_code":"M","country_code":"SE"},{"id":"115855","name":"JONSTORP","state_code":"M","country_code":"SE"},{"id":"115856","name":"KÅGERÖD","state_code":"M","country_code":"SE"},{"id":"115857","name":"KÄVLINGE","state_code":"M","country_code":"SE"},{"id":"115858","name":"KLÅGERUP","state_code":"M","country_code":"SE"},{"id":"115859","name":"KLIPPAN","state_code":"M","country_code":"SE"},{"id":"115860","name":"KNISLINGE","state_code":"M","country_code":"SE"},{"id":"115861","name":"KÖPINGEBRO","state_code":"M","country_code":"SE"},{"id":"115862","name":"KRISTIANSTAD","state_code":"M","country_code":"SE"},{"id":"115863","name":"KVIDINGE","state_code":"M","country_code":"SE"},{"id":"115864","name":"LANDSKRONA","state_code":"M","country_code":"SE"},{"id":"115865","name":"LJUNGBYHED","state_code":"M","country_code":"SE"},{"id":"115866","name":"LJUNGHUSEN","state_code":"M","country_code":"SE"},{"id":"115867","name":"LÖBERÖD","state_code":"M","country_code":"SE"},{"id":"115868","name":"LÖDDEKÖPINGE","state_code":"M","country_code":"SE"},{"id":"115869","name":"LOMMA","state_code":"M","country_code":"SE"},{"id":"115870","name":"LÖNSBODA","state_code":"M","country_code":"SE"},{"id":"115871","name":"LUND","state_code":"M","country_code":"SE"},{"id":"115872","name":"MALMÖ","state_code":"M","country_code":"SE"},{"id":"115873","name":"MARIEHOLM","state_code":"M","country_code":"SE"},{"id":"115874","name":"MÖRARP","state_code":"M","country_code":"SE"},{"id":"115875","name":"MUNKA-LJUNGBY","state_code":"M","country_code":"SE"},{"id":"115876","name":"NÄSUM","state_code":"M","country_code":"SE"},{"id":"115877","name":"NORRA ÅSUM","state_code":"M","country_code":"SE"},{"id":"115878","name":"ÖDÅKRA","state_code":"M","country_code":"SE"},{"id":"115879","name":"ÖNNESTAD","state_code":"M","country_code":"SE"},{"id":"115880","name":"ÖRKELLJUNGA","state_code":"M","country_code":"SE"},{"id":"115881","name":"OSBY","state_code":"M","country_code":"SE"},{"id":"115882","name":"ÖSTRA LJUNGBY","state_code":"M","country_code":"SE"},{"id":"115883","name":"OXIE","state_code":"M","country_code":"SE"},{"id":"115884","name":"PÅARP","state_code":"M","country_code":"SE"},{"id":"115885","name":"PERSTORP","state_code":"M","country_code":"SE"},{"id":"115886","name":"RYDEBÄCK","state_code":"M","country_code":"SE"},{"id":"115887","name":"RYDSGÅRD","state_code":"M","country_code":"SE"},{"id":"115888","name":"SÄTOFTA","state_code":"M","country_code":"SE"},{"id":"115889","name":"SAXTORPSSKOGEN","state_code":"M","country_code":"SE"},{"id":"115890","name":"SIBBHULT","state_code":"M","country_code":"SE"},{"id":"115891","name":"SIMRISHAMN","state_code":"M","country_code":"SE"},{"id":"115892","name":"SJÖBO","state_code":"M","country_code":"SE"},{"id":"115893","name":"SKANÖR MED FALSTERBO","state_code":"M","country_code":"SE"},{"id":"115894","name":"SKÅRE","state_code":"M","country_code":"SE"},{"id":"115895","name":"SKEGRIE","state_code":"M","country_code":"SE"},{"id":"115896","name":"SKIVARP","state_code":"M","country_code":"SE"},{"id":"115897","name":"SKURUP","state_code":"M","country_code":"SE"},{"id":"115898","name":"SMYGEHAMN","state_code":"M","country_code":"SE"},{"id":"115899","name":"SÖDRA SANDBY","state_code":"M","country_code":"SE"},{"id":"115900","name":"SÖSDALA","state_code":"M","country_code":"SE"},{"id":"115901","name":"STAFFANSTORP","state_code":"M","country_code":"SE"},{"id":"115902","name":"STÅNGBY","state_code":"M","country_code":"SE"},{"id":"115903","name":"STEHAG","state_code":"M","country_code":"SE"},{"id":"115904","name":"STRÖVELSTORP","state_code":"M","country_code":"SE"},{"id":"115905","name":"SVALÖV","state_code":"M","country_code":"SE"},{"id":"115906","name":"SVEDALA","state_code":"M","country_code":"SE"},{"id":"115907","name":"TECKOMATORP","state_code":"M","country_code":"SE"},{"id":"115908","name":"TOLLARP","state_code":"M","country_code":"SE"},{"id":"115909","name":"TOLLARP1","state_code":"M","country_code":"SE"},{"id":"115910","name":"TOMELILLA","state_code":"M","country_code":"SE"},{"id":"115911","name":"TOREKOV","state_code":"M","country_code":"SE"},{"id":"115912","name":"TORMESTORP","state_code":"M","country_code":"SE"},{"id":"115913","name":"TRELLEBORG","state_code":"M","country_code":"SE"},{"id":"115914","name":"TYGELSJÖ","state_code":"M","country_code":"SE"},{"id":"115915","name":"TYRINGE","state_code":"M","country_code":"SE"},{"id":"115916","name":"VALJE","state_code":"M","country_code":"SE"},{"id":"115917","name":"VEBERÖD","state_code":"M","country_code":"SE"},{"id":"115918","name":"VEJBYSTRAND","state_code":"M","country_code":"SE"},{"id":"115919","name":"VELLINGE","state_code":"M","country_code":"SE"},{"id":"115920","name":"VIKEN","state_code":"M","country_code":"SE"},{"id":"115921","name":"VINSLÖV","state_code":"M","country_code":"SE"},{"id":"115922","name":"VITTSJÖ","state_code":"M","country_code":"SE"},{"id":"115923","name":"YSTAD","state_code":"M","country_code":"SE"}]