[{"id":97755,"name":"Bagrationovsk","state_id":1902,"state_code":"KGD","state_name":"Kaliningrad","country_id":182,"country_code":"RU","country_name":"Russia"},{"id":97784,"name":"Baltiysk","state_id":1902,"state_code":"KGD","state_name":"Kaliningrad","country_id":182,"country_code":"RU","country_name":"Russia"},{"id":97989,"name":"Bol'shoe Isakovo","state_id":1902,"state_code":"KGD","state_name":"Kaliningrad","country_id":182,"country_code":"RU","country_name":"Russia"},{"id":98177,"name":"Chernyakhovsk","state_id":1902,"state_code":"KGD","state_name":"Kaliningrad","country_id":182,"country_code":"RU","country_name":"Russia"},{"id":98316,"name":"Donskoye","state_id":1902,"state_code":"KGD","state_name":"Kaliningrad","country_id":182,"country_code":"RU","country_name":"Russia"},{"id":98616,"name":"Gur’yevsk","state_id":1902,"state_code":"KGD","state_name":"Kaliningrad","country_id":182,"country_code":"RU","country_name":"Russia"},{"id":98618,"name":"Gusev","state_id":1902,"state_code":"KGD","state_name":"Kaliningrad","country_id":182,"country_code":"RU","country_name":"Russia"},{"id":98624,"name":"Gvardeysk","state_id":1902,"state_code":"KGD","state_name":"Kaliningrad","country_id":182,"country_code":"RU","country_name":"Russia"},{"id":98787,"name":"Kaliningrad","state_id":1902,"state_code":"KGD","state_name":"Kaliningrad","country_id":182,"country_code":"RU","country_name":"Russia"},{"id":99013,"name":"Khrabrovo","state_id":1902,"state_code":"KGD","state_name":"Kaliningrad","country_id":182,"country_code":"RU","country_name":"Russia"},{"id":99356,"name":"Krasnoznamensk","state_id":1902,"state_code":"KGD","state_name":"Kaliningrad","country_id":182,"country_code":"RU","country_name":"Russia"},{"id":99534,"name":"Ladushkin","state_id":1902,"state_code":"KGD","state_name":"Kaliningrad","country_id":182,"country_code":"RU","country_name":"Russia"},{"id":99769,"name":"Maloye Isakovo","state_id":1902,"state_code":"KGD","state_name":"Kaliningrad","country_id":182,"country_code":"RU","country_name":"Russia"},{"id":99777,"name":"Mamonovo","state_id":1902,"state_code":"KGD","state_name":"Kaliningrad","country_id":182,"country_code":"RU","country_name":"Russia"},{"id":100100,"name":"Neman","state_id":1902,"state_code":"KGD","state_name":"Kaliningrad","country_id":182,"country_code":"RU","country_name":"Russia"},{"id":100101,"name":"Nemanskiy Rayon","state_id":1902,"state_code":"KGD","state_name":"Kaliningrad","country_id":182,"country_code":"RU","country_name":"Russia"},{"id":100111,"name":"Nesterov","state_id":1902,"state_code":"KGD","state_name":"Kaliningrad","country_id":182,"country_code":"RU","country_name":"Russia"},{"id":100113,"name":"Nesterovskiy Rayon","state_id":1902,"state_code":"KGD","state_name":"Kaliningrad","country_id":182,"country_code":"RU","country_name":"Russia"},{"id":100507,"name":"Otradnoye","state_id":1902,"state_code":"KGD","state_name":"Kaliningrad","country_id":182,"country_code":"RU","country_name":"Russia"},{"id":100524,"name":"Ozërsk","state_id":1902,"state_code":"KGD","state_name":"Kaliningrad","country_id":182,"country_code":"RU","country_name":"Russia"},{"id":100520,"name":"Ozerskiy Rayon","state_id":1902,"state_code":"KGD","state_name":"Kaliningrad","country_id":182,"country_code":"RU","country_name":"Russia"},{"id":100680,"name":"Pionerskiy","state_id":1902,"state_code":"KGD","state_name":"Kaliningrad","country_id":182,"country_code":"RU","country_name":"Russia"},{"id":100753,"name":"Polessk","state_id":1902,"state_code":"KGD","state_name":"Kaliningrad","country_id":182,"country_code":"RU","country_name":"Russia"},{"id":100802,"name":"Pravdinsk","state_id":1902,"state_code":"KGD","state_name":"Kaliningrad","country_id":182,"country_code":"RU","country_name":"Russia"},{"id":100830,"name":"Primorsk","state_id":1902,"state_code":"KGD","state_name":"Kaliningrad","country_id":182,"country_code":"RU","country_name":"Russia"},{"id":101402,"name":"Slavsk","state_id":1902,"state_code":"KGD","state_name":"Kaliningrad","country_id":182,"country_code":"RU","country_name":"Russia"},{"id":101403,"name":"Slavskiy Rayon","state_id":1902,"state_code":"KGD","state_name":"Kaliningrad","country_id":182,"country_code":"RU","country_name":"Russia"},{"id":101504,"name":"Sovetsk","state_id":1902,"state_code":"KGD","state_name":"Kaliningrad","country_id":182,"country_code":"RU","country_name":"Russia"},{"id":101701,"name":"Svetlogorsk","state_id":1902,"state_code":"KGD","state_name":"Kaliningrad","country_id":182,"country_code":"RU","country_name":"Russia"},{"id":101705,"name":"Svetlyy","state_id":1902,"state_code":"KGD","state_name":"Kaliningrad","country_id":182,"country_code":"RU","country_name":"Russia"},{"id":102350,"name":"Volochayevskoye","state_id":1902,"state_code":"KGD","state_name":"Kaliningrad","country_id":182,"country_code":"RU","country_name":"Russia"},{"id":102456,"name":"Vzmorye","state_id":1902,"state_code":"KGD","state_name":"Kaliningrad","country_id":182,"country_code":"RU","country_name":"Russia"},{"id":102486,"name":"Yantarnyy","state_id":1902,"state_code":"KGD","state_name":"Kaliningrad","country_id":182,"country_code":"RU","country_name":"Russia"},{"id":102619,"name":"Yuzhnyy","state_id":1902,"state_code":"KGD","state_name":"Kaliningrad","country_id":182,"country_code":"RU","country_name":"Russia"},{"id":102699,"name":"Zelenogradsk","state_id":1902,"state_code":"KGD","state_name":"Kaliningrad","country_id":182,"country_code":"RU","country_name":"Russia"},{"id":102718,"name":"Zheleznodorozhnyy","state_id":1902,"state_code":"KGD","state_name":"Kaliningrad","country_id":182,"country_code":"RU","country_name":"Russia"},{"id":102758,"name":"Znamensk","state_id":1902,"state_code":"KGD","state_name":"Kaliningrad","country_id":182,"country_code":"RU","country_name":"Russia"}]