[{"id":"65335","name":"BOUS","state_code":"RM","country_code":"LU"},{"id":"65336","name":"DALHEIM","state_code":"RM","country_code":"LU"},{"id":"65337","name":"LENNINGEN","state_code":"RM","country_code":"LU"},{"id":"65338","name":"MONDORF-LES-BAINS","state_code":"RM","country_code":"LU"},{"id":"65339","name":"REMICH","state_code":"RM","country_code":"LU"},{"id":"65340","name":"SCHENGEN","state_code":"RM","country_code":"LU"},{"id":"65341","name":"STADTBREDIMUS","state_code":"RM","country_code":"LU"},{"id":"65342","name":"WALDBREDIMUS","state_code":"RM","country_code":"LU"}]