[{"id":152,"name":"Ballsh","iso2":"AL","country_name":"Albania","state_name":"Fier County","state_code":"04"},{"id":157,"name":"Bashkia Divjakë","iso2":"AL","country_name":"Albania","state_name":"Fier County","state_code":"04"},{"id":160,"name":"Bashkia Fier","iso2":"AL","country_name":"Albania","state_name":"Fier County","state_code":"04"},{"id":174,"name":"Bashkia Mallakastër","iso2":"AL","country_name":"Albania","state_name":"Fier County","state_code":"04"},{"id":179,"name":"Bashkia Patos","iso2":"AL","country_name":"Albania","state_name":"Fier County","state_code":"04"},{"id":196,"name":"Divjakë","iso2":"AL","country_name":"Albania","state_name":"Fier County","state_code":"04"},{"id":200,"name":"Fier","iso2":"AL","country_name":"Albania","state_name":"Fier County","state_code":"04"},{"id":201,"name":"Fier-Çifçi","iso2":"AL","country_name":"Albania","state_name":"Fier County","state_code":"04"},{"id":227,"name":"Lushnjë","iso2":"AL","country_name":"Albania","state_name":"Fier County","state_code":"04"},{"id":234,"name":"Patos","iso2":"AL","country_name":"Albania","state_name":"Fier County","state_code":"04"},{"id":235,"name":"Patos Fshat","iso2":"AL","country_name":"Albania","state_name":"Fier County","state_code":"04"},{"id":241,"name":"Roskovec","iso2":"AL","country_name":"Albania","state_name":"Fier County","state_code":"04"},{"id":254,"name":"Rrethi i Mallakastrës","iso2":"AL","country_name":"Albania","state_name":"Fier County","state_code":"04"}]