[{"id":"120698","name":"AHMETLI","state_code":"45","country_code":"TR"},{"id":"120699","name":"AKHISAR","state_code":"45","country_code":"TR"},{"id":"120700","name":"ALAŞEHIR","state_code":"45","country_code":"TR"},{"id":"120701","name":"DEMIRCI","state_code":"45","country_code":"TR"},{"id":"120702","name":"GÖLMARMARA","state_code":"45","country_code":"TR"},{"id":"120703","name":"GÖRDES","state_code":"45","country_code":"TR"},{"id":"120704","name":"KIRKAĞAÇ","state_code":"45","country_code":"TR"},{"id":"120705","name":"KÖPRÜBAŞI","state_code":"45","country_code":"TR"},{"id":"120706","name":"KULA","state_code":"45","country_code":"TR"},{"id":"120707","name":"MANISA","state_code":"45","country_code":"TR"},{"id":"120708","name":"SALIHLI İLÇESI","state_code":"45","country_code":"TR"},{"id":"120709","name":"SARIGÖL","state_code":"45","country_code":"TR"},{"id":"120710","name":"SARUHANLI","state_code":"45","country_code":"TR"},{"id":"120711","name":"ŞEHZADELER","state_code":"45","country_code":"TR"},{"id":"120712","name":"SELENDI","state_code":"45","country_code":"TR"},{"id":"120713","name":"SOMA","state_code":"45","country_code":"TR"},{"id":"120714","name":"TURGUTLU İLÇESI","state_code":"45","country_code":"TR"},{"id":"120715","name":"YUNUSEMRE","state_code":"45","country_code":"TR"},{"id":"120716","name":"ZEYTINLIOVA","state_code":"45","country_code":"TR"}]