[{"id":56285,"name":"Gorontalo","iso2":"ID","country_name":"Indonesia","state_name":"Gorontalo","state_code":"GO"},{"id":56365,"name":"Kabupaten Boalemo","iso2":"ID","country_name":"Indonesia","state_name":"Gorontalo","state_code":"GO"},{"id":56375,"name":"Kabupaten Bone Bolango","iso2":"ID","country_name":"Indonesia","state_name":"Gorontalo","state_code":"GO"},{"id":56410,"name":"Kabupaten Gorontalo","iso2":"ID","country_name":"Indonesia","state_name":"Gorontalo","state_code":"GO"},{"id":56411,"name":"Kabupaten Gorontalo Utara","iso2":"ID","country_name":"Indonesia","state_name":"Gorontalo","state_code":"GO"},{"id":56595,"name":"Kabupaten Pohuwato","iso2":"ID","country_name":"Indonesia","state_name":"Gorontalo","state_code":"GO"},{"id":56753,"name":"Kota Gorontalo","iso2":"ID","country_name":"Indonesia","state_name":"Gorontalo","state_code":"GO"}]