[{"id":"77932","name":"EL CUÁ","state_code":"JI","country_code":"NI"},{"id":"77933","name":"JINOTEGA","state_code":"JI","country_code":"NI"},{"id":"77934","name":"LA CONCORDIA","state_code":"JI","country_code":"NI"},{"id":"77935","name":"LAS PRADERAS","state_code":"JI","country_code":"NI"},{"id":"77936","name":"LLANO DE LA CRUZ","state_code":"JI","country_code":"NI"},{"id":"77937","name":"SAN JOSÉ DE BOCAY","state_code":"JI","country_code":"NI"},{"id":"77938","name":"SAN RAFAEL DEL NORTE","state_code":"JI","country_code":"NI"},{"id":"77939","name":"SAN SEBASTIÁN DE YALÍ","state_code":"JI","country_code":"NI"}]