[{"id":17358,"name":"Aarberg","iso2":"CH","country_name":"Switzerland","state_name":"Bern","state_code":"BE"},{"id":17360,"name":"Aarwangen","iso2":"CH","country_name":"Switzerland","state_name":"Bern","state_code":"BE"},{"id":17362,"name":"Adelboden","iso2":"CH","country_name":"Switzerland","state_name":"Bern","state_code":"BE"},{"id":17373,"name":"Aeschi b. Spiez","iso2":"CH","country_name":"Switzerland","state_name":"Bern","state_code":"BE"},{"id":17404,"name":"Arch","iso2":"CH","country_name":"Switzerland","state_name":"Bern","state_code":"BE"},{"id":17417,"name":"Attiswil","iso2":"CH","country_name":"Switzerland","state_name":"Bern","state_code":"BE"},{"id":17592,"name":"Bäriswil","iso2":"CH","country_name":"Switzerland","state_name":"Bern","state_code":"BE"},{"id":17593,"name":"Bätterkinden","iso2":"CH","country_name":"Switzerland","state_name":"Bern","state_code":"BE"},{"id":17447,"name":"Beatenberg","iso2":"CH","country_name":"Switzerland","state_name":"Bern","state_code":"BE"},{"id":17454,"name":"Bellmund","iso2":"CH","country_name":"Switzerland","state_name":"Bern","state_code":"BE"},{"id":17456,"name":"Belp","iso2":"CH","country_name":"Switzerland","state_name":"Bern","state_code":"BE"},{"id":17462,"name":"Bern","iso2":"CH","country_name":"Switzerland","state_name":"Bern","state_code":"BE"},{"id":17463,"name":"Bern-Mittelland District","iso2":"CH","country_name":"Switzerland","state_name":"Bern","state_code":"BE"},{"id":17594,"name":"Bévilard","iso2":"CH","country_name":"Switzerland","state_name":"Bern","state_code":"BE"},{"id":17526,"name":"Biel\/Bienne","iso2":"CH","country_name":"Switzerland","state_name":"Bern","state_code":"BE"},{"id":17527,"name":"Biel\/Bienne District","iso2":"CH","country_name":"Switzerland","state_name":"Bern","state_code":"BE"},{"id":17528,"name":"Biglen","iso2":"CH","country_name":"Switzerland","state_name":"Bern","state_code":"BE"},{"id":17542,"name":"Blumenstein","iso2":"CH","country_name":"Switzerland","state_name":"Bern","state_code":"BE"},{"id":17545,"name":"Bolligen","iso2":"CH","country_name":"Switzerland","state_name":"Bern","state_code":"BE"},{"id":17546,"name":"Boltigen","iso2":"CH","country_name":"Switzerland","state_name":"Bern","state_code":"BE"},{"id":17595,"name":"Bönigen","iso2":"CH","country_name":"Switzerland","state_name":"Bern","state_code":"BE"},{"id":17556,"name":"Bowil","iso2":"CH","country_name":"Switzerland","state_name":"Bern","state_code":"BE"},{"id":17560,"name":"Brienz","iso2":"CH","country_name":"Switzerland","state_name":"Bern","state_code":"BE"},{"id":17572,"name":"Brügg","iso2":"CH","country_name":"Switzerland","state_name":"Bern","state_code":"BE"},{"id":17577,"name":"Buchholterberg","iso2":"CH","country_name":"Switzerland","state_name":"Bern","state_code":"BE"},{"id":17583,"name":"Burgdorf","iso2":"CH","country_name":"Switzerland","state_name":"Bern","state_code":"BE"},{"id":17584,"name":"Burgistein","iso2":"CH","country_name":"Switzerland","state_name":"Bern","state_code":"BE"},{"id":17653,"name":"Corgémont","iso2":"CH","country_name":"Switzerland","state_name":"Bern","state_code":"BE"},{"id":17664,"name":"Court","iso2":"CH","country_name":"Switzerland","state_name":"Bern","state_code":"BE"},{"id":17665,"name":"Courtelary","iso2":"CH","country_name":"Switzerland","state_name":"Bern","state_code":"BE"},{"id":17708,"name":"Därligen","iso2":"CH","country_name":"Switzerland","state_name":"Bern","state_code":"BE"},{"id":17686,"name":"Diemtigen","iso2":"CH","country_name":"Switzerland","state_name":"Bern","state_code":"BE"},{"id":17716,"name":"Dürrenroth","iso2":"CH","country_name":"Switzerland","state_name":"Bern","state_code":"BE"},{"id":17731,"name":"Eggiwil","iso2":"CH","country_name":"Switzerland","state_name":"Bern","state_code":"BE"},{"id":17747,"name":"Emmental District","iso2":"CH","country_name":"Switzerland","state_name":"Bern","state_code":"BE"},{"id":17758,"name":"Eriswil","iso2":"CH","country_name":"Switzerland","state_name":"Bern","state_code":"BE"},{"id":17759,"name":"Erlach","iso2":"CH","country_name":"Switzerland","state_name":"Bern","state_code":"BE"},{"id":17764,"name":"Erlenbach im Simmental","iso2":"CH","country_name":"Switzerland","state_name":"Bern","state_code":"BE"},{"id":17767,"name":"Ersigen","iso2":"CH","country_name":"Switzerland","state_name":"Bern","state_code":"BE"},{"id":17777,"name":"Evilard","iso2":"CH","country_name":"Switzerland","state_name":"Bern","state_code":"BE"},{"id":17784,"name":"Ferenbalm","iso2":"CH","country_name":"Switzerland","state_name":"Bern","state_code":"BE"},{"id":17802,"name":"Fraubrunnen","iso2":"CH","country_name":"Switzerland","state_name":"Bern","state_code":"BE"},{"id":17805,"name":"Frauenkappelen","iso2":"CH","country_name":"Switzerland","state_name":"Bern","state_code":"BE"},{"id":17812,"name":"Frutigen","iso2":"CH","country_name":"Switzerland","state_name":"Bern","state_code":"BE"},{"id":17813,"name":"Frutigen-Niedersimmental District","iso2":"CH","country_name":"Switzerland","state_name":"Bern","state_code":"BE"},{"id":17870,"name":"Grindelwald","iso2":"CH","country_name":"Switzerland","state_name":"Bern","state_code":"BE"},{"id":17874,"name":"Grossaffoltern","iso2":"CH","country_name":"Switzerland","state_name":"Bern","state_code":"BE"},{"id":17884,"name":"Gstaad","iso2":"CH","country_name":"Switzerland","state_name":"Bern","state_code":"BE"},{"id":17885,"name":"Guggisberg","iso2":"CH","country_name":"Switzerland","state_name":"Bern","state_code":"BE"},{"id":17902,"name":"Heimberg","iso2":"CH","country_name":"Switzerland","state_name":"Bern","state_code":"BE"},{"id":17903,"name":"Heimiswil","iso2":"CH","country_name":"Switzerland","state_name":"Bern","state_code":"BE"},{"id":17908,"name":"Hermiswil","iso2":"CH","country_name":"Switzerland","state_name":"Bern","state_code":"BE"},{"id":17910,"name":"Herzogenbuchsee","iso2":"CH","country_name":"Switzerland","state_name":"Bern","state_code":"BE"},{"id":17913,"name":"Hilterfingen","iso2":"CH","country_name":"Switzerland","state_name":"Bern","state_code":"BE"},{"id":17915,"name":"Hindelbank","iso2":"CH","country_name":"Switzerland","state_name":"Bern","state_code":"BE"},{"id":17936,"name":"Huttwil","iso2":"CH","country_name":"Switzerland","state_name":"Bern","state_code":"BE"},{"id":17952,"name":"Ins","iso2":"CH","country_name":"Switzerland","state_name":"Bern","state_code":"BE"},{"id":17953,"name":"Interlaken","iso2":"CH","country_name":"Switzerland","state_name":"Bern","state_code":"BE"},{"id":17954,"name":"Interlaken-Oberhasli District","iso2":"CH","country_name":"Switzerland","state_name":"Bern","state_code":"BE"},{"id":17957,"name":"Jegenstorf","iso2":"CH","country_name":"Switzerland","state_name":"Bern","state_code":"BE"},{"id":17963,"name":"Jura bernois","iso2":"CH","country_name":"Switzerland","state_name":"Bern","state_code":"BE"},{"id":17968,"name":"Kallnach","iso2":"CH","country_name":"Switzerland","state_name":"Bern","state_code":"BE"},{"id":17970,"name":"Kandersteg","iso2":"CH","country_name":"Switzerland","state_name":"Bern","state_code":"BE"},{"id":17971,"name":"Kappelen","iso2":"CH","country_name":"Switzerland","state_name":"Bern","state_code":"BE"},{"id":17972,"name":"Kehrsatz","iso2":"CH","country_name":"Switzerland","state_name":"Bern","state_code":"BE"},{"id":17981,"name":"Kirchberg","iso2":"CH","country_name":"Switzerland","state_name":"Bern","state_code":"BE"},{"id":17982,"name":"Kirchlindach","iso2":"CH","country_name":"Switzerland","state_name":"Bern","state_code":"BE"},{"id":18011,"name":"Köniz","iso2":"CH","country_name":"Switzerland","state_name":"Bern","state_code":"BE"},{"id":18002,"name":"Konolfingen","iso2":"CH","country_name":"Switzerland","state_name":"Bern","state_code":"BE"},{"id":18003,"name":"Koppigen","iso2":"CH","country_name":"Switzerland","state_name":"Bern","state_code":"BE"},{"id":18004,"name":"Krauchthal","iso2":"CH","country_name":"Switzerland","state_name":"Bern","state_code":"BE"},{"id":18023,"name":"La Neuveville","iso2":"CH","country_name":"Switzerland","state_name":"Bern","state_code":"BE"},{"id":18036,"name":"Langenthal","iso2":"CH","country_name":"Switzerland","state_name":"Bern","state_code":"BE"},{"id":18037,"name":"Langnau","iso2":"CH","country_name":"Switzerland","state_name":"Bern","state_code":"BE"},{"id":18045,"name":"Laupen","iso2":"CH","country_name":"Switzerland","state_name":"Bern","state_code":"BE"},{"id":18047,"name":"Lauperswil","iso2":"CH","country_name":"Switzerland","state_name":"Bern","state_code":"BE"},{"id":18051,"name":"Lauterbrunnen","iso2":"CH","country_name":"Switzerland","state_name":"Bern","state_code":"BE"},{"id":18063,"name":"Lengnau","iso2":"CH","country_name":"Switzerland","state_name":"Bern","state_code":"BE"},{"id":18064,"name":"Lenk","iso2":"CH","country_name":"Switzerland","state_name":"Bern","state_code":"BE"},{"id":18077,"name":"Leuzigen","iso2":"CH","country_name":"Switzerland","state_name":"Bern","state_code":"BE"},{"id":18085,"name":"Linden","iso2":"CH","country_name":"Switzerland","state_name":"Bern","state_code":"BE"},{"id":18093,"name":"Lotzwil","iso2":"CH","country_name":"Switzerland","state_name":"Bern","state_code":"BE"},{"id":18112,"name":"Lützelflüh","iso2":"CH","country_name":"Switzerland","state_name":"Bern","state_code":"BE"},{"id":18107,"name":"Lyss","iso2":"CH","country_name":"Switzerland","state_name":"Bern","state_code":"BE"},{"id":18108,"name":"Lyssach","iso2":"CH","country_name":"Switzerland","state_name":"Bern","state_code":"BE"},{"id":18113,"name":"Madiswil","iso2":"CH","country_name":"Switzerland","state_name":"Bern","state_code":"BE"},{"id":18118,"name":"Malleray","iso2":"CH","country_name":"Switzerland","state_name":"Bern","state_code":"BE"},{"id":18129,"name":"Matten","iso2":"CH","country_name":"Switzerland","state_name":"Bern","state_code":"BE"},{"id":18142,"name":"Meinisberg","iso2":"CH","country_name":"Switzerland","state_name":"Bern","state_code":"BE"},{"id":18143,"name":"Meiringen","iso2":"CH","country_name":"Switzerland","state_name":"Bern","state_code":"BE"},{"id":18146,"name":"Melchnau","iso2":"CH","country_name":"Switzerland","state_name":"Bern","state_code":"BE"},{"id":18175,"name":"Moutier","iso2":"CH","country_name":"Switzerland","state_name":"Bern","state_code":"BE"},{"id":18195,"name":"Mühleberg","iso2":"CH","country_name":"Switzerland","state_name":"Bern","state_code":"BE"},{"id":18197,"name":"Mühlethurnen","iso2":"CH","country_name":"Switzerland","state_name":"Bern","state_code":"BE"},{"id":18199,"name":"Münchenbuchsee","iso2":"CH","country_name":"Switzerland","state_name":"Bern","state_code":"BE"},{"id":18201,"name":"Münchenwiler","iso2":"CH","country_name":"Switzerland","state_name":"Bern","state_code":"BE"},{"id":18204,"name":"Münsingen","iso2":"CH","country_name":"Switzerland","state_name":"Bern","state_code":"BE"},{"id":18206,"name":"Müntschemier","iso2":"CH","country_name":"Switzerland","state_name":"Bern","state_code":"BE"},{"id":18183,"name":"Muri","iso2":"CH","country_name":"Switzerland","state_name":"Bern","state_code":"BE"},{"id":18219,"name":"Nidau","iso2":"CH","country_name":"Switzerland","state_name":"Bern","state_code":"BE"},{"id":18220,"name":"Niederbipp","iso2":"CH","country_name":"Switzerland","state_name":"Bern","state_code":"BE"},{"id":18239,"name":"Oberaargau","iso2":"CH","country_name":"Switzerland","state_name":"Bern","state_code":"BE"},{"id":18240,"name":"Oberbipp","iso2":"CH","country_name":"Switzerland","state_name":"Bern","state_code":"BE"},{"id":18242,"name":"Oberburg","iso2":"CH","country_name":"Switzerland","state_name":"Bern","state_code":"BE"},{"id":18243,"name":"Oberdiessbach","iso2":"CH","country_name":"Switzerland","state_name":"Bern","state_code":"BE"},{"id":18267,"name":"Obersimmental-Saanen District","iso2":"CH","country_name":"Switzerland","state_name":"Bern","state_code":"BE"},{"id":18289,"name":"Orpund","iso2":"CH","country_name":"Switzerland","state_name":"Bern","state_code":"BE"},{"id":18291,"name":"Orvin","iso2":"CH","country_name":"Switzerland","state_name":"Bern","state_code":"BE"},{"id":18332,"name":"Péry","iso2":"CH","country_name":"Switzerland","state_name":"Bern","state_code":"BE"},{"id":18314,"name":"Pieterlen","iso2":"CH","country_name":"Switzerland","state_name":"Bern","state_code":"BE"},{"id":18334,"name":"Radelfingen","iso2":"CH","country_name":"Switzerland","state_name":"Bern","state_code":"BE"},{"id":18343,"name":"Reconvilier","iso2":"CH","country_name":"Switzerland","state_name":"Bern","state_code":"BE"},{"id":18376,"name":"Riggisberg","iso2":"CH","country_name":"Switzerland","state_name":"Bern","state_code":"BE"},{"id":18377,"name":"Ringgenberg","iso2":"CH","country_name":"Switzerland","state_name":"Bern","state_code":"BE"},{"id":18382,"name":"Roggwil","iso2":"CH","country_name":"Switzerland","state_name":"Bern","state_code":"BE"},{"id":18385,"name":"Rohrbach","iso2":"CH","country_name":"Switzerland","state_name":"Bern","state_code":"BE"},{"id":18396,"name":"Rubigen","iso2":"CH","country_name":"Switzerland","state_name":"Bern","state_code":"BE"},{"id":18404,"name":"Rüderswil","iso2":"CH","country_name":"Switzerland","state_name":"Bern","state_code":"BE"},{"id":18405,"name":"Rüeggisberg","iso2":"CH","country_name":"Switzerland","state_name":"Bern","state_code":"BE"},{"id":18408,"name":"Rüschegg","iso2":"CH","country_name":"Switzerland","state_name":"Bern","state_code":"BE"},{"id":18415,"name":"Saanen","iso2":"CH","country_name":"Switzerland","state_name":"Bern","state_code":"BE"},{"id":18425,"name":"Saint-Imier","iso2":"CH","country_name":"Switzerland","state_name":"Bern","state_code":"BE"},{"id":18443,"name":"Sankt Stephan","iso2":"CH","country_name":"Switzerland","state_name":"Bern","state_code":"BE"},{"id":18488,"name":"Schüpfen","iso2":"CH","country_name":"Switzerland","state_name":"Bern","state_code":"BE"},{"id":18491,"name":"Seeberg","iso2":"CH","country_name":"Switzerland","state_name":"Bern","state_code":"BE"},{"id":18493,"name":"Seedorf","iso2":"CH","country_name":"Switzerland","state_name":"Bern","state_code":"BE"},{"id":18494,"name":"Seeland District","iso2":"CH","country_name":"Switzerland","state_name":"Bern","state_code":"BE"},{"id":18502,"name":"Seftigen","iso2":"CH","country_name":"Switzerland","state_name":"Bern","state_code":"BE"},{"id":18519,"name":"Signau","iso2":"CH","country_name":"Switzerland","state_name":"Bern","state_code":"BE"},{"id":18520,"name":"Sigriswil","iso2":"CH","country_name":"Switzerland","state_name":"Bern","state_code":"BE"},{"id":18533,"name":"Spiez","iso2":"CH","country_name":"Switzerland","state_name":"Bern","state_code":"BE"},{"id":18550,"name":"Steffisburg","iso2":"CH","country_name":"Switzerland","state_name":"Bern","state_code":"BE"},{"id":18558,"name":"Stettlen","iso2":"CH","country_name":"Switzerland","state_name":"Bern","state_code":"BE"},{"id":18566,"name":"Sumiswald","iso2":"CH","country_name":"Switzerland","state_name":"Bern","state_code":"BE"},{"id":18617,"name":"Täuffelen","iso2":"CH","country_name":"Switzerland","state_name":"Bern","state_code":"BE"},{"id":18576,"name":"Tavannes","iso2":"CH","country_name":"Switzerland","state_name":"Bern","state_code":"BE"},{"id":18590,"name":"Thierachern","iso2":"CH","country_name":"Switzerland","state_name":"Bern","state_code":"BE"},{"id":18591,"name":"Thun","iso2":"CH","country_name":"Switzerland","state_name":"Bern","state_code":"BE"},{"id":18592,"name":"Thun District","iso2":"CH","country_name":"Switzerland","state_name":"Bern","state_code":"BE"},{"id":18597,"name":"Toffen","iso2":"CH","country_name":"Switzerland","state_name":"Bern","state_code":"BE"},{"id":18598,"name":"Trachselwald","iso2":"CH","country_name":"Switzerland","state_name":"Bern","state_code":"BE"},{"id":18599,"name":"Tramelan","iso2":"CH","country_name":"Switzerland","state_name":"Bern","state_code":"BE"},{"id":18608,"name":"Trub","iso2":"CH","country_name":"Switzerland","state_name":"Bern","state_code":"BE"},{"id":18609,"name":"Trubschachen","iso2":"CH","country_name":"Switzerland","state_name":"Bern","state_code":"BE"},{"id":18626,"name":"Uetendorf","iso2":"CH","country_name":"Switzerland","state_name":"Bern","state_code":"BE"},{"id":18635,"name":"Unterseen","iso2":"CH","country_name":"Switzerland","state_name":"Bern","state_code":"BE"},{"id":18644,"name":"Urtenen","iso2":"CH","country_name":"Switzerland","state_name":"Bern","state_code":"BE"},{"id":18651,"name":"Uttigen","iso2":"CH","country_name":"Switzerland","state_name":"Bern","state_code":"BE"},{"id":18653,"name":"Utzenstorf","iso2":"CH","country_name":"Switzerland","state_name":"Bern","state_code":"BE"},{"id":18663,"name":"Vechigen","iso2":"CH","country_name":"Switzerland","state_name":"Bern","state_code":"BE"},{"id":18714,"name":"Walkringen","iso2":"CH","country_name":"Switzerland","state_name":"Bern","state_code":"BE"},{"id":18723,"name":"Wangen an der Aare","iso2":"CH","country_name":"Switzerland","state_name":"Bern","state_code":"BE"},{"id":18724,"name":"Wattenwil","iso2":"CH","country_name":"Switzerland","state_name":"Bern","state_code":"BE"},{"id":18744,"name":"Wichtrach","iso2":"CH","country_name":"Switzerland","state_name":"Bern","state_code":"BE"},{"id":18745,"name":"Wiedlisbach","iso2":"CH","country_name":"Switzerland","state_name":"Bern","state_code":"BE"},{"id":18752,"name":"Wilderswil","iso2":"CH","country_name":"Switzerland","state_name":"Bern","state_code":"BE"},{"id":18756,"name":"Wimmis","iso2":"CH","country_name":"Switzerland","state_name":"Bern","state_code":"BE"},{"id":18762,"name":"Wohlen","iso2":"CH","country_name":"Switzerland","state_name":"Bern","state_code":"BE"},{"id":18768,"name":"Worb","iso2":"CH","country_name":"Switzerland","state_name":"Bern","state_code":"BE"},{"id":18769,"name":"Worben","iso2":"CH","country_name":"Switzerland","state_name":"Bern","state_code":"BE"},{"id":18770,"name":"Wynau","iso2":"CH","country_name":"Switzerland","state_name":"Bern","state_code":"BE"},{"id":18771,"name":"Wynigen","iso2":"CH","country_name":"Switzerland","state_name":"Bern","state_code":"BE"},{"id":18772,"name":"Wyssachen","iso2":"CH","country_name":"Switzerland","state_name":"Bern","state_code":"BE"},{"id":18808,"name":"Zäziwil","iso2":"CH","country_name":"Switzerland","state_name":"Bern","state_code":"BE"},{"id":18798,"name":"Zollikofen","iso2":"CH","country_name":"Switzerland","state_name":"Bern","state_code":"BE"},{"id":18806,"name":"Zweisimmen","iso2":"CH","country_name":"Switzerland","state_name":"Bern","state_code":"BE"}]